vnpy_websocket/__init__.py
vnpy_websocket/websocket_client.py
vnpy_websocket-1.0.6.dist-info/LICENSE
vnpy_websocket-1.0.6.dist-info/METADATA
vnpy_websocket-1.0.6.dist-info/WHEEL
vnpy_websocket-1.0.6.dist-info/top_level.txt
vnpy_websocket-1.0.6.dist-info/RECORD
